essahtmlgen/__init__.py
essahtmlgen/essahtmlgen.py
essahtmlgen/data/CSU_Logo.jpg
essahtmlgen-4.3.dist-info/AUTHORS
essahtmlgen-4.3.dist-info/METADATA
essahtmlgen-4.3.dist-info/WHEEL
essahtmlgen-4.3.dist-info/entry_points.txt
essahtmlgen-4.3.dist-info/top_level.txt
essahtmlgen-4.3.dist-info/RECORD
